rnasa/__init__.py
rnasa/cli/__init__.py
rnasa/cli/main.py
rnasa/cli/tpm.py
rnasa/static/urls.yml
rnasa/task/__init__.py
rnasa/task/controller.py
rnasa/task/core.py
rnasa/task/rsem.py
rnasa-0.2.0.dist-info/LICENSE
rnasa-0.2.0.dist-info/METADATA
rnasa-0.2.0.dist-info/WHEEL
rnasa-0.2.0.dist-info/entry_points.txt
rnasa-0.2.0.dist-info/top_level.txt
rnasa-0.2.0.dist-info/RECORD
