Metadata-Version: 2.1
Name: rnasa
Version: 0.2.0
Summary: Gene Expression Level Calculator for RNA-seq
Home-page: https://github.com/dceoy/rnasa
Author: Daichi Narushima
Author-email: dnarsil+github@gmail.com
Classifier: Development Status :: 4 - Beta
Classifier: Environment :: Console
Classifier: Intended Audience :: Science/Research
Classifier: Intended Audience :: Healthcare Industry
Classifier: License :: OSI Approved :: MIT License
Classifier: Operating System :: MacOS
Classifier: Operating System :: MacOS :: MacOS X
Classifier: Operating System :: POSIX
Classifier: Operating System :: POSIX :: Linux
Classifier: Operating System :: Unix
Classifier: Programming Language :: Python
Classifier: Programming Language :: Python :: 3
Classifier: Topic :: Scientific/Engineering
Classifier: Topic :: Scientific/Engineering :: Bio-Informatics
Classifier: Topic :: Scientific/Engineering :: Medical Science Apps.
Requires-Python: >=3.6
License-File: LICENSE
Requires-Dist: docopt
Requires-Dist: ftarc
Requires-Dist: luigi
Requires-Dist: pandas
Requires-Dist: psutil
